{"id":"0z44t6egu1zh6v6w1biro7c","title":"hypergamy","desc":"","updated":1655451582763,"created":1655441183942,"tags":"sociology","custom":{},"fname":"concepts.hypergamy","type":"note","vault":{"fsPath":".","selfContained":true,"name":"Dendron"},"contentHash":"0492344cd9416f308059c591dc6d9bf8","links":[{"type":"frontmatterTag","from":{"fname":"concepts.hypergamy","id":"0z44t6egu1zh6v6w1biro7c","vaultName":"Dendron"},"value":"tags.sociology","alias":"sociology","xvault":false,"to":{"fname":"tags.sociology"}}],"anchors":{},"children":[],"parent":"4zumv5du4dtnq25bkcd3mua","data":{}}
