{"id":"bfqk7lwe4kg1bvq42lm4iqw","title":"Empiriomonism","desc":"","updated":1655441183941,"created":1655441183941,"tags":"philosophy/empiricism","custom":{},"fname":"concepts.empiriomonism","type":"note","vault":{"fsPath":".","selfContained":true,"name":"Dendron"},"contentHash":"89758e9c281c605b94ce460a4e157f7d","links":[{"type":"frontmatterTag","from":{"fname":"concepts.empiriomonism","id":"bfqk7lwe4kg1bvq42lm4iqw","vaultName":"Dendron"},"value":"tags.philosophy/empiricism","alias":"philosophy/empiricism","xvault":false,"to":{"fname":"tags.philosophy/empiricism"}},{"type":"wiki","from":{"fname":"concepts.empiriomonism","id":"bfqk7lwe4kg1bvq42lm4iqw","vaultName":"Dendron"},"value":"alexander-bogdanov's","alias":"Alexander Bogdanov","position":{"start":{"line":2,"column":19,"offset":19},"end":{"line":2,"column":62,"offset":62},"indent":[]},"xvault":false,"sameFile":false,"to":{"fname":"alexander-bogdanov's"}},{"type":"wiki","from":{"fname":"concepts.empiriomonism","id":"bfqk7lwe4kg1bvq42lm4iqw","vaultName":"Dendron"},"value":"concepts.noiré's-labor-theory-of-language-developmen","alias":"concepts.noiré's-labor-theory-of-language-developmen","position":{"start":{"line":2,"column":175,"offset":175},"end":{"line":2,"column":269,"offset":269},"indent":[]},"xvault":false,"sameFile":false,"to":{"fname":"concepts.noiré's-labor-theory-of-language-developmen"}},{"type":"wiki","from":{"fname":"concepts.empiriomonism","id":"bfqk7lwe4kg1bvq42lm4iqw","vaultName":"Dendron"},"value":"tektology","alias":"tektology","position":{"start":{"line":4,"column":374,"offset":752},"end":{"line":4,"column":387,"offset":765},"indent":[]},"xvault":false,"sameFile":false,"to":{"fname":"tektology"}},{"type":"wiki","from":{"fname":"concepts.empiriomonism","id":"bfqk7lwe4kg1bvq42lm4iqw","vaultName":"Dendron"},"value":"empiriomonism-(book)","alias":"empiriomonism-(book)","position":{"start":{"line":7,"column":3,"offset":785},"end":{"line":7,"column":27,"offset":809},"indent":[]},"xvault":false,"sameFile":false,"to":{"fname":"empiriomonism-(book)"}}],"anchors":{"references":{"type":"header","text":"References","value":"references","line":13,"column":0,"depth":2}},"children":[],"parent":"4zumv5du4dtnq25bkcd3mua","data":{}}
