{"id":"hgv1zn9n4gzobgvc0ow6r78","title":"master-slave dialectic","desc":"","updated":1655535649885,"created":1655441183942,"tags":"philosophy","custom":{},"fname":"concepts.master-slave-dialectic","type":"note","vault":{"fsPath":".","selfContained":true,"name":"Dendron"},"contentHash":"50099350b366b2a01b7beb4c6bdac74c","links":[{"type":"frontmatterTag","from":{"fname":"concepts.master-slave-dialectic","id":"hgv1zn9n4gzobgvc0ow6r78","vaultName":"Dendron"},"value":"tags.philosophy","alias":"philosophy","xvault":false,"to":{"fname":"tags.philosophy"}},{"type":"wiki","from":{"fname":"concepts.master-slave-dialectic","id":"hgv1zn9n4gzobgvc0ow6r78","vaultName":"Dendron"},"value":"e.slave-societies-weaken-masters","alias":"e.slave-societies-weaken-masters","position":{"start":{"line":6,"column":102,"offset":905},"end":{"line":6,"column":138,"offset":941},"indent":[]},"xvault":false,"sameFile":false,"to":{"fname":"e.slave-societies-weaken-masters"}}],"anchors":{},"children":[],"parent":"44mv0lvtkoofskdmnqfgo2o","data":{}}
