{"fname":"unproven","stub":true,"vault":{"fsPath":".","selfContained":true,"name":"Dendron"},"schemaStub":false,"type":"note","updated":1655455875889,"created":1655455875889,"id":"jrq580aoxokgsj0g83s364q","desc":"","links":[],"anchors":{},"children":["o109h1ksk3mcpoiqa4e2g1v","m8mtjsyk1atkcc7f6k7ly2f","my67vtpaucsrm1wdlkubz3q","94fhz4o5myvm3mo7m6nvgnu","auf701k94hkfpnc4zppw01z","x28h73rru5a278nz2rvy632","hd6l2wkxkjg4ln44cl7zs4b","5bav4h83johai443dr6zqz4","q0xaqg5az4z60epwp6d8oq2","7pnn7h6e3n69xz8pjg0q8ba"],"parent":"tivrplnoaurusggrx2rxbz3","data":{},"title":"Unproven"}
