{"id":"jsdokce2cu8ksvkpdfb3wb5","title":"smychka","desc":"","updated":1655441183943,"created":1655441183943,"tags":"history/russia/ussr","custom":{},"fname":"concepts.marxism.smychka","type":"note","vault":{"fsPath":".","selfContained":true,"name":"Dendron"},"contentHash":"7da0f3438a5e90e3b3c4389399d82ee2","links":[{"type":"frontmatterTag","from":{"fname":"concepts.marxism.smychka","id":"jsdokce2cu8ksvkpdfb3wb5","vaultName":"Dendron"},"value":"tags.history/russia/ussr","alias":"history/russia/ussr","xvault":false,"to":{"fname":"tags.history/russia/ussr"}},{"type":"wiki","from":{"fname":"concepts.marxism.smychka","id":"jsdokce2cu8ksvkpdfb3wb5","vaultName":"Dendron"},"value":"bukharin","alias":"Nikolai Bukharin","position":{"start":{"line":2,"column":129,"offset":129},"end":{"line":2,"column":158,"offset":158},"indent":[]},"xvault":false,"sameFile":false,"to":{"fname":"bukharin"}}],"anchors":{},"children":[],"parent":"391shjvar6bmlhasttsc036","data":{}}
